dj_angles/__init__.py
dj_angles/attributes.py
dj_angles/caseconverter/LICENSE
dj_angles/caseconverter/README.md
dj_angles/caseconverter/__init__.py
dj_angles/caseconverter/boundaries.py
dj_angles/caseconverter/caseconverter.py
dj_angles/caseconverter/kebab.py
dj_angles/evaluator.py
dj_angles/exceptions.py
dj_angles/htmls.py
dj_angles/mappers/__init__.py
dj_angles/mappers/angles.py
dj_angles/mappers/django.py
dj_angles/mappers/include.py
dj_angles/mappers/mapper.py
dj_angles/mappers/thirdparty.py
dj_angles/middleware.py
dj_angles/modules.py
dj_angles/quote_utils.py
dj_angles/replacers/__init__.py
dj_angles/replacers/attributes.py
dj_angles/replacers/objects.py
dj_angles/replacers/tags.py
dj_angles/replacers/variables.py
dj_angles/settings.py
dj_angles/static/dj_angles/js/ajax-form.js
dj_angles/strings.py
dj_angles/tags.py
dj_angles/template_loader.py
dj_angles/templates/dj_angles/scripts.html
dj_angles/templates.py
dj_angles/templatetags/__init__.py
dj_angles/templatetags/call.py
dj_angles/templatetags/dj_angles.py
dj_angles/templatetags/model.py
dj_angles/templatetags/template.py
dj_angles/tokenizer.py
dj_angles-0.25.0.dist-info/WHEEL
dj_angles-0.25.0.dist-info/METADATA
dj_angles-0.25.0.dist-info/RECORD
