Metadata-Version: 2.3
Name: dj-angles
Version: 0.25.0
Summary: Add more bracket angles to Django templates </>
Keywords: Django,HTML,brackets,Django Template Language,Django Template Partials,Component Library
Author: Adam Hill
Author-email: Adam Hill <adam@adamghill.com>
License: MIT License
Classifier: Development Status :: 3 - Alpha
Classifier: Intended Audience :: Developers
Classifier: License :: OSI Approved :: MIT License
Classifier: Programming Language :: Python :: 3.10
Classifier: Programming Language :: Python :: 3.11
Classifier: Programming Language :: Python :: 3.12
Classifier: Programming Language :: Python :: 3.13
Classifier: Programming Language :: Python :: 3.14
Classifier: Framework :: Django
Classifier: Framework :: Django :: 4
Classifier: Framework :: Django :: 5
Classifier: Framework :: Django :: 6
Requires-Dist: django>=0
Requires-Dist: minestrone>=0.9.0
Requires-Dist: django-bird>=0 ; extra == 'bird'
Requires-Dist: django-components>=0 ; extra == 'components'
Requires-Dist: django-template-partials>=0 ; extra == 'template-partials'
Requires-Python: >=3.10
Project-URL: Changelog, https://dj-angles.adamghill.com/en/latest/changelog.html
Project-URL: Documentation, https://dj-angles.adamghill.com
Project-URL: Homepage, https://dj-angles.adamghill.com
Project-URL: Issues, https://github.com/adamghill/dj-angles/discussions
Project-URL: Repository, https://github.com/adamghill/dj-angles.git
Provides-Extra: bird
Provides-Extra: components
Provides-Extra: template-partials
